MANIFEST.in
setup.cfg
setup.py
versioneer.py
tcx/__init__.py
tcx/__version__.py
tcx.egg-info/PKG-INFO
tcx.egg-info/SOURCES.txt
tcx.egg-info/dependency_links.txt
tcx.egg-info/requires.txt
tcx.egg-info/top_level.txt
tcx.egg-info/zip-safe